<?xml version='1.0' encoding='ISO-8859-1'?>
<validator onerror='/action/error/validation/ajax'>
	<parameter id='spr_solicitud' type='integer' required='false' label='${lbl:b_request_number}' maxlen='10'/>
	<parameter id='smn_auxiliar' type='integer' required='true' label='${lbl:b_auxiliary}' maxlen='10'/>
	<parameter id='smn_contratante_id' type='integer' required='false' label='${lbl:b_contratante_aux}' maxlen='10'/>
	<!-- <parameter id='smn_patologia_id' type='integer' required='true' label='${lbl:b_pathology}' maxlen='10'/> -->
	<parameter id='spr_dias_hospitalizacion' type='integer' required='true' label='${lbl:b_hospitalization_day}' maxlen='10'/>
	<parameter id='spr_horas_quirofano' type='integer' required='true' label='${lbl:b_operating_room_hours}' maxlen='10'/>
	<parameter id='spr_instrumentales' type='varchar' required='false' label='${lbl:b_instrumentals}' maxlen='250'/>
	<parameter id='spr_honorarios' type='integer' required='true' label='${lbl:b_schedules}' maxlen='10'/>
	<parameter id='spr_estatus' type='varchar' required='false' label='${lbl:b_estatus}' maxlen='2'/>
	<parameter id='smn_presupuesto_id' type='integer' required='false' label='${lbl:b_auxiliary}' maxlen='10'/>
	<parameter id='smn_documento_id' type='integer' required='false' label='${lbl:b_auxiliary}' maxlen='10'/>
    
    <parameter id='smn_servicios_rf' type='varchar' required='false' label='Ítems'/>
	<custom-validator classname='dinamica.validators.StringToRecordset' paramName='smn_servicios_rf' recordsetId='query-smnservicios.sql' separatorChar=';' colName='smn_servicios_rf' colType='integer'/>
	
	<parameter id='smn_activo_fijo_rf' type='varchar' required='true' label='Ítems'/>
	<custom-validator classname='dinamica.validators.StringToRecordset' paramName='smn_activo_fijo_rf' recordsetId='query-smnactivo.sql' separatorChar=';' colName='smn_activo_fijo_rf' colType='integer'/>

	<parameter id='smn_patologia_id' type='varchar' required='true' label='Ítems'/>
	<custom-validator classname='dinamica.validators.StringToRecordset' paramName='smn_patologia_id' recordsetId='query-smnpatologias.sql' separatorChar=';' colName='smn_patologia_id' colType='integer'/>

<!-- 	<parameter id='smn_honorarios_id' type='varchar' required='true' label='Ítems'/>
	<custom-validator classname='dinamica.validators.StringToRecordset' paramName='smn_honorarios_id' recordsetId='query-smnhonorarios.sql' separatorChar=';' colName='smn_honorarios_id' colType='integer'/> -->

</validator>
